pyviddler/__init__.py
pyviddler/api.py
pyviddler/encoding.py
pyviddler/exceptions.py
pyviddler/logins.py
pyviddler/playlists.py
pyviddler/resellers.py
pyviddler/tests.py
pyviddler/users.py
pyviddler/viddler.py
pyviddler/videos.py
pyviddler-0.5.dist-info/DESCRIPTION.rst
pyviddler-0.5.dist-info/METADATA
pyviddler-0.5.dist-info/RECORD
pyviddler-0.5.dist-info/WHEEL
pyviddler-0.5.dist-info/metadata.json
pyviddler-0.5.dist-info/pbr.json
pyviddler-0.5.dist-info/top_level.txt
