Metadata-Version: 2.0
Name: pyviddler
Version: 0.5
Summary: This provides a Python wrapper around Viddler's v2 API.
Home-page: https://github.com/callowayproject/pyviddler
Author: Corey Oordt
Author-email: webmaster@callowayproject.com
License: UNKNOWN
Platform: UNKNOWN
Requires-Dist: requests
